README.rst
setup.py
sumpf/__init__.py
sumpf.egg-info/PKG-INFO
sumpf.egg-info/SOURCES.txt
sumpf.egg-info/dependency_links.txt
sumpf.egg-info/requires.txt
sumpf.egg-info/top_level.txt
sumpf/_blocks/__init__.py
sumpf/_blocks/_concatenate.py
sumpf/_blocks/_jack.py
sumpf/_blocks/_merge.py
sumpf/_data/__init__.py
sumpf/_data/_sampled_data.py
sumpf/_data/_filters/__init__.py
sumpf/_data/_filters/_bands.py
sumpf/_data/_filters/_bessel.py
sumpf/_data/_filters/_butterworth.py
sumpf/_data/_filters/_chebyshev.py
sumpf/_data/_filters/_delay.py
sumpf/_data/_filters/_derivative.py
sumpf/_data/_filters/_weighting.py
sumpf/_data/_filters/_base/__init__.py
sumpf/_data/_filters/_base/_filter.py
sumpf/_data/_filters/_base/_functions.py
sumpf/_data/_filters/_base/_iir.py
sumpf/_data/_filters/_base/_s.py
sumpf/_data/_filters/_base/_terms/__init__.py
sumpf/_data/_filters/_base/_terms/_base.py
sumpf/_data/_filters/_base/_terms/_binary.py
sumpf/_data/_filters/_base/_terms/_primitive.py
sumpf/_data/_filters/_base/_terms/_unary.py
sumpf/_data/_signals/__init__.py
sumpf/_data/_signals/_constant.py
sumpf/_data/_signals/_energy_decay.py
sumpf/_data/_signals/_fade.py
sumpf/_data/_signals/_mls.py
sumpf/_data/_signals/_noise.py
sumpf/_data/_signals/_signal.py
sumpf/_data/_signals/_sweep.py
sumpf/_data/_signals/_waves.py
sumpf/_data/_signals/_windows.py
sumpf/_data/_signals/_windows_scipy.py
sumpf/_data/_spectrograms/__init__.py
sumpf/_data/_spectrograms/_constant.py
sumpf/_data/_spectrograms/_spectrogram.py
sumpf/_data/_spectrums/__init__.py
sumpf/_data/_spectrums/_constant.py
sumpf/_data/_spectrums/_rudinshapiro.py
sumpf/_data/_spectrums/_spectrum.py
sumpf/_internal/__init__.py
sumpf/_internal/_convolution.py
sumpf/_internal/_enums.py
sumpf/_internal/_functions.py
sumpf/_internal/_indexing.py
sumpf/_internal/_interpolation.py
sumpf/_internal/_text.py
sumpf/_internal/_persistence/__init__.py
sumpf/_internal/_persistence/_auto_writer.py
sumpf/_internal/_persistence/_filter_readers.py
sumpf/_internal/_persistence/_filter_writers.py
sumpf/_internal/_persistence/_functions.py
sumpf/_internal/_persistence/_signal_readers.py
