Metadata-Version: 2.1
Name: sumpf
Version: 0.17
Summary: A signal processing package with a focus on acoustics
Home-page: https://github.com/JonasSC/SuMPF
Author: Jonas Schulte-Coerne
License: GNU Lesser General Public License v3 or later (LGPLv3+)
Project-URL: Documentation, https://sumpf.readthedocs.io/en/latest/
Project-URL: Bug Reports, https://github.com/JonasSC/SuMPF/issues
Project-URL: Source, https://github.com/JonasSC/SuMPF
Keywords: signal-processing acoustics
Platform: UNKNOWN
Classifier: Development Status :: 5 - Production/Stable
Classifier: License :: OSI Approved :: GNU Lesser General Public License v3 or later (LGPLv3+)
Classifier: Programming Language :: Python :: 3.7
Classifier: Intended Audience :: Developers
Classifier: Intended Audience :: Science/Research
Classifier: Topic :: Software Development :: Libraries :: Application Frameworks
Provides-Extra: dev
Provides-Extra: test
